[ { "id": "0", "name": "Unknown", "shortName": "UNK" },
  { "id": "700", "name": "Afghanistan", "shortName": "AFG" },
  { "id": "339", "name": "Albania", "shortName": "ALB" },
  { "id": "615", "name": "Algeria", "shortName": "ALG" },
  { "id": "232", "name": "Andorra", "shortName": "AND" },
  { "id": "540", "name": "Angola", "shortName": "ANG" },
  { "id": "58", "name": "Antigua & Barbuda", "shortName": "AAB" },
  { "id": "160", "name": "Argentina", "shortName": "ARG" },
  { "id": "371", "name": "Armenia", "shortName": "ARM" },
  { "id": "900", "name": "Australia", "shortName": "AUL" },
  { "id": "305", "name": "Austria", "shortName": "AUS" },
  { "id": "300", "name": "Austria-Hungary", "shortName": "AUH" },
  { "id": "373", "name": "Azerbaijan", "shortName": "AZE" },
  { "id": "267", "name": "Baden", "shortName": "BAD" },
  { "id": "31", "name": "Bahamas", "shortName": "BHM" },
  { "id": "692", "name": "Bahrain", "shortName": "BAH" },
  { "id": "771", "name": "Bangladesh", "shortName": "BNG" },
  { "id": "53", "name": "Barbados", "shortName": "BAR" },
  { "id": "245", "name": "Bavaria", "shortName": "BAV" },
  { "id": "370", "name": "Belarus", "shortName": "BLR" },
  { "id": "211", "name": "Belgium", "shortName": "BEL" },
  { "id": "80", "name": "Belize", "shortName": "BLZ" },
  { "id": "434", "name": "Benin", "shortName": "BEN" },
  { "id": "760", "name": "Bhutan", "shortName": "BHU" },
  { "id": "145", "name": "Bolivia", "shortName": "BOL" },
  { "id": "346", "name": "Bosnia and Herzegovina", "shortName": "BOS" },
  { "id": "571", "name": "Botswana", "shortName": "BOT" },
  { "id": "140", "name": "Brazil", "shortName": "BRA" },
  { "id": "835", "name": "Brunei", "shortName": "BRU" },
  { "id": "355", "name": "Bulgaria", "shortName": "BUL" },
  { "id": "439", "name": "Burkina Faso", "shortName": "BFO" },
  { "id": "516", "name": "Burundi", "shortName": "BUI" },
  { "id": "811", "name": "Cambodia", "shortName": "CAM" },
  { "id": "471", "name": "Cameroon", "shortName": "CAO" },
  { "id": "20", "name": "Canada", "shortName": "CAN" },
  { "id": "402", "name": "Cape Verde", "shortName": "CAP" },
  { "id": "482", "name": "Central African Republic", "shortName": "CEN" },
  { "id": "483", "name": "Chad", "shortName": "CHA" },
  { "id": "155", "name": "Chile", "shortName": "CHL" },
  { "id": "710", "name": "China", "shortName": "CHN" },
  { "id": "100", "name": "Colombia", "shortName": "COL" },
  { "id": "581", "name": "Comoros", "shortName": "COM" },
  { "id": "484", "name": "Congo", "shortName": "CON" },
  { "id": "94", "name": "Costa Rica", "shortName": "COS" },
  { "id": "344", "name": "Croatia", "shortName": "CRO" },
  { "id": "40", "name": "Cuba", "shortName": "CUB" },
  { "id": "352", "name": "Cyprus", "shortName": "CYP" },
  { "id": "315", "name": "Czechoslovakia", "shortName": "CZE" },
  { "id": "316", "name": "Czech Republic", "shortName": "CZR" },
  { "id": "490",
    "name": "Democratic Republic of the Congo",
    "shortName": "DRC" },
  { "id": "390", "name": "Denmark", "shortName": "DEN" },
  { "id": "522", "name": "Djibouti", "shortName": "DJI" },
  { "id": "54", "name": "Dominica", "shortName": "DMA" },
  { "id": "42", "name": "Dominican Republic", "shortName": "DOM" },
  { "id": "860", "name": "East Timor", "shortName": "ETM" },
  { "id": "130", "name": "Ecuador", "shortName": "ECU" },
  { "id": "651", "name": "Egypt", "shortName": "EGY" },
  { "id": "92", "name": "El Salvador", "shortName": "SAL" },
  { "id": "411", "name": "Equatorial Guinea", "shortName": "EQG" },
  { "id": "531", "name": "Eritrea", "shortName": "ERI" },
  { "id": "366", "name": "Estonia", "shortName": "EST" },
  { "id": "530", "name": "Ethiopia", "shortName": "ETH" },
  { "id": "987",
    "name": "Federated States of Micronesia",
    "shortName": "FSM" },
  { "id": "950", "name": "Fiji", "shortName": "FIJ" },
  { "id": "375", "name": "Finland", "shortName": "FIN" },
  { "id": "220", "name": "France", "shortName": "FRN" },
  { "id": "481", "name": "Gabon", "shortName": "GAB" },
  { "id": "420", "name": "Gambia", "shortName": "GAM" },
  { "id": "372", "name": "Georgia", "shortName": "GRG" },
  { "id": "265",
    "name": "German Democratic Republic",
    "shortName": "GDR" },
  { "id": "260", "name": "German Federal Republic", "shortName": "GFR" },
  { "id": "255", "name": "Germany", "shortName": "GMY" },
  { "id": "452", "name": "Ghana", "shortName": "GHA" },
  { "id": "350", "name": "Greece", "shortName": "GRC" },
  { "id": "55", "name": "Grenada", "shortName": "GRN" },
  { "id": "90", "name": "Guatemala", "shortName": "GUA" },
  { "id": "438", "name": "Guinea", "shortName": "GUI" },
  { "id": "404", "name": "Guinea-Bissau", "shortName": "GNB" },
  { "id": "110", "name": "Guyana", "shortName": "GUY" },
  { "id": "41", "name": "Haiti", "shortName": "HAI" },
  { "id": "240", "name": "Hanover", "shortName": "HAN" },
  { "id": "273", "name": "Hesse Electoral", "shortName": "HSE" },
  { "id": "275", "name": "Hesse Grand Ducal", "shortName": "HSG" },
  { "id": "91", "name": "Honduras", "shortName": "HON" },
  { "id": "310", "name": "Hungary", "shortName": "HUN" },
  { "id": "395", "name": "Iceland", "shortName": "ICE" },
  { "id": "750", "name": "India", "shortName": "IND" },
  { "id": "850", "name": "Indonesia", "shortName": "INS" },
  { "id": "630", "name": "Iran", "shortName": "IRN" },
  { "id": "645", "name": "Iraq", "shortName": "IRQ" },
  { "id": "205", "name": "Ireland", "shortName": "IRE" },
  { "id": "666", "name": "Israel", "shortName": "ISR" },
  { "id": "325", "name": "Italy", "shortName": "ITA" },
  { "id": "437", "name": "Ivory Coast", "shortName": "CDI" },
  { "id": "51", "name": "Jamaica", "shortName": "JAM" },
  { "id": "740", "name": "Japan", "shortName": "JPN" },
  { "id": "663", "name": "Jordan", "shortName": "JOR" },
  { "id": "705", "name": "Kazakhstan", "shortName": "KZK" },
  { "id": "501", "name": "Kenya", "shortName": "KEN" },
  { "id": "946", "name": "Kiribati", "shortName": "KIR" },
  { "id": "730", "name": "Korea", "shortName": "KOR" },
  { "id": "347", "name": "Kosovo", "shortName": "KOS" },
  { "id": "690", "name": "Kuwait", "shortName": "KUW" },
  { "id": "703", "name": "Kyrgyzstan", "shortName": "KYR" },
  { "id": "812", "name": "Laos", "shortName": "LAO" },
  { "id": "367", "name": "Latvia", "shortName": "LAT" },
  { "id": "660", "name": "Lebanon", "shortName": "LEB" },
  { "id": "570", "name": "Lesotho", "shortName": "LES" },
  { "id": "450", "name": "Liberia", "shortName": "LBR" },
  { "id": "620", "name": "Libya", "shortName": "LIB" },
  { "id": "223", "name": "Liechtenstein", "shortName": "LIE" },
  { "id": "368", "name": "Lithuania", "shortName": "LIT" },
  { "id": "212", "name": "Luxembourg", "shortName": "LUX" },
  { "id": "343", "name": "Macedonia", "shortName": "MAC" },
  { "id": "580", "name": "Madagascar", "shortName": "MAG" },
  { "id": "553", "name": "Malawi", "shortName": "MAW" },
  { "id": "820", "name": "Malaysia", "shortName": "MAL" },
  { "id": "781", "name": "Maldives", "shortName": "MAD" },
  { "id": "432", "name": "Mali", "shortName": "MLI" },
  { "id": "338", "name": "Malta", "shortName": "MLT" },
  { "id": "983", "name": "Marshall Islands", "shortName": "MSI" },
  { "id": "435", "name": "Mauritania", "shortName": "MAA" },
  { "id": "590", "name": "Mauritius", "shortName": "MAS" },
  { "id": "280", "name": "Mecklenburg Schwerin", "shortName": "MEC" },
  { "id": "70", "name": "Mexico", "shortName": "MEX" },
  { "id": "332", "name": "Modena", "shortName": "MOD" },
  { "id": "359", "name": "Moldova", "shortName": "MLD" },
  { "id": "221", "name": "Monaco", "shortName": "MNC" },
  { "id": "712", "name": "Mongolia", "shortName": "MON" },
  { "id": "341", "name": "Montenegro", "shortName": "MNG" },
  { "id": "600", "name": "Morocco", "shortName": "MOR" },
  { "id": "541", "name": "Mozambique", "shortName": "MZM" },
  { "id": "775", "name": "Myanmar", "shortName": "MYA" },
  { "id": "565", "name": "Namibia", "shortName": "NAM" },
  { "id": "970", "name": "Nauru", "shortName": "NAU" },
  { "id": "790", "name": "Nepal", "shortName": "NEP" },
  { "id": "210", "name": "Netherlands", "shortName": "NTH" },
  { "id": "920", "name": "New Zealand", "shortName": "NEW" },
  { "id": "93", "name": "Nicaragua", "shortName": "NIC" },
  { "id": "436", "name": "Niger", "shortName": "NIR" },
  { "id": "475", "name": "Nigeria", "shortName": "NIG" },
  { "id": "731", "name": "North Korea", "shortName": "PRK" },
  { "id": "385", "name": "Norway", "shortName": "NOR" },
  { "id": "698", "name": "Oman", "shortName": "OMA" },
  { "id": "770", "name": "Pakistan", "shortName": "PAK" },
  { "id": "986", "name": "Palau", "shortName": "PAL" },
  { "id": "95", "name": "Panama", "shortName": "PAN" },
  { "id": "327", "name": "Papal States", "shortName": "PAP" },
  { "id": "910", "name": "Papua New Guinea", "shortName": "PNG" },
  { "id": "150", "name": "Paraguay", "shortName": "PAR" },
  { "id": "335", "name": "Parma", "shortName": "PMA" },
  { "id": "135", "name": "Peru", "shortName": "PER" },
  { "id": "840", "name": "Philippines", "shortName": "PHI" },
  { "id": "290", "name": "Poland", "shortName": "POL" },
  { "id": "235", "name": "Portugal", "shortName": "POR" },
  { "id": "694", "name": "Qatar", "shortName": "QAT" },
  { "id": "817", "name": "Republic of Vietnam", "shortName": "RVN" },
  { "id": "360", "name": "Romania", "shortName": "ROM" },
  { "id": "365", "name": "Russia", "shortName": "RUS" },
  { "id": "517", "name": "Rwanda", "shortName": "RWA" },
  { "id": "990", "name": "Samoa", "shortName": "WSM" },
  { "id": "331", "name": "San Marino", "shortName": "SNM" },
  { "id": "403", "name": "Sao Tome and Principe", "shortName": "STP" },
  { "id": "670", "name": "Saudi Arabia", "shortName": "SAU" },
  { "id": "269", "name": "Saxony", "shortName": "SAX" },
  { "id": "433", "name": "Senegal", "shortName": "SEN" },
  { "id": "591", "name": "Seychelles", "shortName": "SEY" },
  { "id": "451", "name": "Sierra Leone", "shortName": "SIE" },
  { "id": "830", "name": "Singapore", "shortName": "SIN" },
  { "id": "317", "name": "Slovakia", "shortName": "SLO" },
  { "id": "349", "name": "Slovenia", "shortName": "SLV" },
  { "id": "940", "name": "Solomon Islands", "shortName": "SOL" },
  { "id": "520", "name": "Somalia", "shortName": "SOM" },
  { "id": "560", "name": "South Africa", "shortName": "SAF" },
  { "id": "732", "name": "South Korea", "shortName": "ROK" },
  { "id": "626", "name": "South Sudan", "shortName": "SSD" },
  { "id": "230", "name": "Spain", "shortName": "SPN" },
  { "id": "780", "name": "Sri Lanka", "shortName": "SRI" },
  { "id": "60", "name": "St. Kitts and Nevis", "shortName": "SKN" },
  { "id": "56", "name": "St. Lucia", "shortName": "SLU" },
  { "id": "57",
    "name": "St. Vincent and the Grenadines",
    "shortName": "SVG" },
  { "id": "625", "name": "Sudan", "shortName": "SUD" },
  { "id": "115", "name": "Suriname", "shortName": "SUR" },
  { "id": "572", "name": "Swaziland", "shortName": "SWA" },
  { "id": "380", "name": "Sweden", "shortName": "SWD" },
  { "id": "225", "name": "Switzerland", "shortName": "SWZ" },
  { "id": "652", "name": "Syria", "shortName": "SYR" },
  { "id": "713", "name": "Taiwan", "shortName": "TAW" },
  { "id": "702", "name": "Tajikistan", "shortName": "TAJ" },
  { "id": "510", "name": "Tanzania", "shortName": "TAZ" },
  { "id": "800", "name": "Thailand", "shortName": "THI" },
  { "id": "461", "name": "Togo", "shortName": "TOG" },
  { "id": "955", "name": "Tonga", "shortName": "TON" },
  { "id": "52", "name": "Trinidad and Tobago", "shortName": "TRI" },
  { "id": "616", "name": "Tunisia", "shortName": "TUN" },
  { "id": "640", "name": "Turkey", "shortName": "TUR" },
  { "id": "701", "name": "Turkmenistan", "shortName": "TKM" },
  { "id": "337", "name": "Tuscany", "shortName": "TUS" },
  { "id": "947", "name": "Tuvalu", "shortName": "TUV" },
  { "id": "329", "name": "Two Sicilies", "shortName": "SIC" },
  { "id": "500", "name": "Uganda", "shortName": "UGA" },
  { "id": "369", "name": "Ukraine", "shortName": "UKR" },
  { "id": "696", "name": "United Arab Emirates", "shortName": "UAE" },
  { "id": "200", "name": "United Kingdom", "shortName": "UKG" },
  { "id": "2", "name": "United States of America", "shortName": "USA" },
  { "id": "165", "name": "Uruguay", "shortName": "URU" },
  { "id": "704", "name": "Uzbekistan", "shortName": "UZB" },
  { "id": "935", "name": "Vanuatu", "shortName": "VAN" },
  { "id": "101", "name": "Venezuela", "shortName": "VEN" },
  { "id": "816", "name": "Vietnam", "shortName": "DRV" },
  { "id": "271", "name": "Wuerttemburg", "shortName": "WRT" },
  { "id": "679", "name": "Yemen", "shortName": "YEM" },
  { "id": "678", "name": "Yemen Arab Republic", "shortName": "YAR" },
  { "id": "680", "name": "Yemen People\"s Republic", "shortName": "YPR" },
  { "id": "345", "name": "Yugoslavia", "shortName": "YUG" },
  { "id": "551", "name": "Zambia", "shortName": "ZAM" },
  { "id": "511", "name": "Zanzibar", "shortName": "ZAN" },
  { "id": "552", "name": "Zimbabwe", "shortName": "ZIM" } ]
